AK_SSL/__init__.py
AK_SSL/multimodal/Trainer.py
AK_SSL/multimodal/__init__.py
AK_SSL/multimodal/models/__init__.py
AK_SSL/multimodal/models/albef.py
AK_SSL/multimodal/models/clip.py
AK_SSL/multimodal/models/simvlm.py
AK_SSL/multimodal/models/slip.py
AK_SSL/multimodal/models/uniter.py
AK_SSL/multimodal/models/vse.py
AK_SSL/multimodal/models/utils/__init__.py
AK_SSL/multimodal/models/utils/clip/__init__.py
AK_SSL/multimodal/models/utils/clip/datasets.py
AK_SSL/multimodal/models/utils/simvlm/__init__.py
AK_SSL/multimodal/models/utils/simvlm/resblock.py
AK_SSL/vision/Trainer.py
AK_SSL/vision/__init__.py
AK_SSL/vision/models/__init__.py
AK_SSL/vision/models/barlowtwins.py
AK_SSL/vision/models/byol.py
AK_SSL/vision/models/dino.py
AK_SSL/vision/models/evaluate.py
AK_SSL/vision/models/moco.py
AK_SSL/vision/models/simclr.py
AK_SSL/vision/models/simsiam.py
AK_SSL/vision/models/swav.py
AK_SSL/vision/models/modules/__init__.py
AK_SSL/vision/models/modules/heads.py
AK_SSL/vision/models/modules/losses/__init__.py
AK_SSL/vision/models/modules/losses/barlow_twins_loss.py
AK_SSL/vision/models/modules/losses/byol_loss.py
AK_SSL/vision/models/modules/losses/dino_loss.py
AK_SSL/vision/models/modules/losses/info_nce.py
AK_SSL/vision/models/modules/losses/negative_cosine_similarity.py
AK_SSL/vision/models/modules/losses/nt_xent.py
AK_SSL/vision/models/modules/losses/swav_loss.py
AK_SSL/vision/models/modules/transformations/__init__.py
AK_SSL/vision/models/modules/transformations/simclr.py
ak_ssl-0.2.1.dist-info/licenses/LICENSE
ak_ssl-0.2.1.dist-info/METADATA
ak_ssl-0.2.1.dist-info/WHEEL
ak_ssl-0.2.1.dist-info/top_level.txt
ak_ssl-0.2.1.dist-info/RECORD
