Metadata-Version: 2.4
Name: AK_SSL
Version: 0.2.1
Summary: A Self-Supervised Learning Library
Author: Kian Majlessi
Author-email: Audrina Ebrahimi <audrina_ebrahimi@outlook.com>
License: MIT
Project-URL: Homepage, https://github.com/audrina-ebrahimi/AK_SSL
Project-URL: Repository, https://github.com/audrina-ebrahimi/AK_SSL.git
Project-URL: Issues, https://github.com/audrina-ebrahimi/AK_SSL/issues
Keywords: self-supervised learning,contrastive learning,computer vision,multimodal,representation learning,pytorch
Classifier: Development Status :: 3 - Alpha
Classifier: Intended Audience :: Education
Classifier: Intended Audience :: Science/Research
Classifier: Topic :: Scientific/Engineering :: Artificial Intelligence
Classifier: Topic :: Scientific/Engineering :: Image Processing
Classifier: Topic :: Software Development :: Libraries :: Python Modules
Classifier: Programming Language :: Python :: 3
Classifier: Programming Language :: Python :: 3.10
Classifier: Programming Language :: Python :: 3.11
Classifier: License :: OSI Approved :: MIT License
Requires-Python: >=3.10
License-File: LICENSE
Requires-Dist: numpy
Requires-Dist: torch
Requires-Dist: torchvision
Requires-Dist: torcheval
Requires-Dist: tqdm
Requires-Dist: tensorboard
Requires-Dist: wandb
Requires-Dist: einops
Requires-Dist: axial_positional_embedding
Requires-Dist: Pillow
Requires-Dist: transformers
Requires-Dist: wandb
Dynamic: license-file
Dynamic: requires-python
